simplegeoip/__init__.py
simplegeoip/main.py
simplegeoip-0.2.0.dist-info/LICENSE
simplegeoip-0.2.0.dist-info/METADATA
simplegeoip-0.2.0.dist-info/WHEEL
simplegeoip-0.2.0.dist-info/entry_points.txt
simplegeoip-0.2.0.dist-info/top_level.txt
simplegeoip-0.2.0.dist-info/RECORD
