Metadata-Version: 2.1
Name: simplegeoip
Version: 0.2.0
Summary: Shell script and module for easy geoip lookups.
Home-page: https://github.com/Tethik/simplegeoip
Author: Joakim Uddholm
Author-email: tethik@gmail.com
License: GNU GENERAL PUBLIC LICENSE
Requires-Dist: maxminddb
Requires-Dist: requests
Requires-Dist: appdirs
